veridock/__init__.py
veridock/cli/__init__.py
veridock/cli/commands/__init__.py
veridock/cli/commands/init.py
veridock/cli/commands/server.py
veridock/cli/commands/service.py
veridock/cli/utils.py
veridock/grpc_server.py
veridock/http_gateway.py
veridock-0.1.5.dist-info/LICENSE
veridock-0.1.5.dist-info/METADATA
veridock-0.1.5.dist-info/WHEEL
veridock-0.1.5.dist-info/entry_points.txt
veridock-0.1.5.dist-info/RECORD
