Metadata-Version: 2.3
Name: veridock
Version: 0.1.5
Summary: Veridock - gRPC-powered server management tool
License: MIT
Author: Your Name
Author-email: your.email@example.com
Requires-Python: >=3.10,<4.0
Classifier: License :: OSI Approved :: MIT License
Classifier: Programming Language :: Python :: 3
Classifier: Programming Language :: Python :: 3.10
Classifier: Programming Language :: Python :: 3.11
Classifier: Programming Language :: Python :: 3.12
Classifier: Programming Language :: Python :: 3.13
Requires-Dist: click (>=8.1.7,<9.0.0)
Requires-Dist: flask (>=3.1.1,<4.0.0)
Requires-Dist: grpcio (>=1.62.1,<2.0.0)
Requires-Dist: grpcio-tools (>=1.62.1,<2.0.0)
Requires-Dist: protobuf (>=4.25.3,<5.0.0)
Requires-Dist: python-dotenv (>=1.0.0,<2.0.0)
Requires-Dist: requests (>=2.31.0,<3.0.0)
Requires-Dist: werkzeug (>=3.1.3,<4.0.0)
